AUTHORS.rst
CONTRIBUTING.rst
HISTORY.rst
LICENSE
MANIFEST.in
README.rst
setup.cfg
setup.py
docs/Makefile
docs/authors.rst
docs/conf.py
docs/contributing.rst
docs/history.rst
docs/index.rst
docs/installation.rst
docs/make.bat
docs/readme.rst
docs/usage.rst
str_tools/__init__.py
str_tools/cli.py
str_tools/str_tools.py
str_tools.egg-info/PKG-INFO
str_tools.egg-info/SOURCES.txt
str_tools.egg-info/dependency_links.txt
str_tools.egg-info/entry_points.txt
str_tools.egg-info/not-zip-safe
str_tools.egg-info/requires.txt
str_tools.egg-info/top_level.txt
tests/__init__.py
tests/test_str_tools.py