Metadata-Version: 1.1
Name: str-tools
Version: 0.1.5
Summary: Tools for manipulating STR data.
Home-page: https://github.com/GaryCondon/str_tools
Author: Gary Condon
Author-email: gary@condon.net
License: MIT license
Keywords: str_tools
Platform: UNKNOWN
Classifier: Development Status :: 2 - Pre-Alpha
Classifier: Intended Audience :: Developers
Classifier: License :: OSI Approved :: MIT License
Classifier: Natural Language :: English
Classifier: Programming Language :: Python :: 2
Classifier: Programming Language :: Python :: 2.6
Classifier: Programming Language :: Python :: 2.7
Classifier: Programming Language :: Python :: 3
Classifier: Programming Language :: Python :: 3.3
Classifier: Programming Language :: Python :: 3.4
Classifier: Programming Language :: Python :: 3.5
